slow_django/__init__.py
slow_django/middleware.py
slow_django-1.1.0.dist-info/WHEEL
slow_django-1.1.0.dist-info/METADATA
slow_django-1.1.0.dist-info/RECORD
