Metadata-Version: 2.1
Name: slow-django
Version: 1.1.0
Summary: Django, but slower
Home-page: https://github.com/pbexe/slow-django
Author: pbexe
Requires-Python: >=3.7,<4.0
Classifier: Programming Language :: Python :: 3
Classifier: Programming Language :: Python :: 3.7
Classifier: Programming Language :: Python :: 3.8
Requires-Dist: django (>=3.0.7,<4.0.0)
Project-URL: Repository, https://github.com/pbexe/slow-django
